<?xml version="1.0" encoding="UTF-8"?>
<export version="E">
  <design>
    <source>D:\roboscan\vidisco\schematic\ki VCU\VCU\VCU.kicad_sch</source>
    <date>2022-10-21 6:02:11 PM</date>
    <tool>Eeschema (6.0.8)</tool>
    <sheet number="1" name="/" tstamps="/">
      <title_block>
        <title>SINGLE SUPPLY TWISTED PAIR DRIVER</title>
        <company>KOBRAT_AL_TAFAKHOR COM</company>
        <rev/>
        <date>2022-10-16</date>
        <source>VCU.kicad_sch</source>
        <comment number="1" value="THARWAT AGAMY"/>
        <comment number="2" value=""/>
        <comment number="3" value=""/>
        <comment number="4" value=""/>
        <comment number="5" value=""/>
        <comment number="6" value=""/>
        <comment number="7" value=""/>
        <comment number="8" value=""/>
        <comment number="9" value=""/>
      </title_block>
    </sheet>
  </design>
  <components>
    <comp ref="C1">
      <value>220u</value>
      <footprint>Capacitor_THT:CP_Radial_D6.3mm_P2.50mm</footprint>
      <libsource lib="Device" part="C_Polarized" description="Polarized capacitor"/>
      <property name="Sheetname" value=""/>
      <property name="Sheetfile" value="File: VCU.kicad_sch"/>
      <sheetpath names="/" tstamps="/"/>
      <tstamps>5afe5c36-cfb9-4919-9250-2b2f361de683</tstamps>
    </comp>
    <comp ref="C2">
      <value>680p</value>
      <footprint>Capacitor_THT:C_Disc_D3.8mm_W2.6mm_P2.50mm</footprint>
      <libsource lib="Device" part="C" description="Unpolarized capacitor"/>
      <property name="Sheetname" value=""/>
      <property name="Sheetfile" value="File: VCU.kicad_sch"/>
      <sheetpath names="/" tstamps="/"/>
      <tstamps>c0a314ea-f436-4199-a88d-343eaabc795f</tstamps>
    </comp>
    <comp ref="C3">
      <value>100n</value>
      <footprint>Capacitor_THT:C_Disc_D3.8mm_W2.6mm_P2.50mm</footprint>
      <libsource lib="Device" part="C" description="Unpolarized capacitor"/>
      <property name="Sheetname" value=""/>
      <property name="Sheetfile" value="File: VCU.kicad_sch"/>
      <sheetpath names="/" tstamps="/"/>
      <tstamps>e61859ba-e04d-4a2b-9189-72ab36d9e840</tstamps>
    </comp>
    <comp ref="C4">
      <value>100n</value>
      <footprint>Capacitor_THT:C_Disc_D3.8mm_W2.6mm_P2.50mm</footprint>
      <libsource lib="Device" part="C" description="Unpolarized capacitor"/>
      <property name="Sheetname" value=""/>
      <property name="Sheetfile" value="File: VCU.kicad_sch"/>
      <sheetpath names="/" tstamps="/"/>
      <tstamps>a1e3f89f-6efb-4567-83a4-8a60a273364a</tstamps>
    </comp>
    <comp ref="C5">
      <value>4u7</value>
      <footprint>Capacitor_THT:CP_Radial_D6.3mm_P2.50mm</footprint>
      <libsource lib="" part="C_Polarized_1" description="Polarized capacitor"/>
      <property name="Sheetname" value=""/>
      <property name="Sheetfile" value="File: VCU.kicad_sch"/>
      <sheetpath names="/" tstamps="/"/>
      <tstamps>2eec4ddd-1711-40bb-b683-0e109215554e</tstamps>
    </comp>
    <comp ref="C6">
      <value>100n</value>
      <footprint>Capacitor_THT:C_Disc_D3.8mm_W2.6mm_P2.50mm</footprint>
      <libsource lib="Device" part="C" description="Unpolarized capacitor"/>
      <property name="Sheetname" value=""/>
      <property name="Sheetfile" value="File: VCU.kicad_sch"/>
      <sheetpath names="/" tstamps="/"/>
      <tstamps>aa2ad8c8-09a4-42eb-b27f-d2a5fe653d38</tstamps>
    </comp>
    <comp ref="C7">
      <value>100n</value>
      <footprint>Capacitor_THT:C_Disc_D3.8mm_W2.6mm_P2.50mm</footprint>
      <libsource lib="Device" part="C" description="Unpolarized capacitor"/>
      <property name="Sheetname" value=""/>
      <property name="Sheetfile" value="File: VCU.kicad_sch"/>
      <sheetpath names="/" tstamps="/"/>
      <tstamps>4878cde0-3292-4c2a-be6d-f1f10c858e26</tstamps>
    </comp>
    <comp ref="C8">
      <value>100u</value>
      <footprint>Capacitor_THT:CP_Radial_D6.3mm_P2.50mm</footprint>
      <libsource lib="Device" part="C_Polarized" description="Polarized capacitor"/>
      <property name="Sheetname" value=""/>
      <property name="Sheetfile" value="File: VCU.kicad_sch"/>
      <sheetpath names="/" tstamps="/"/>
      <tstamps>44213d00-9393-4929-965c-197f871db8c7</tstamps>
    </comp>
    <comp ref="D1">
      <value>1N4007</value>
      <footprint>Diode_THT:D_DO-41_SOD81_P10.16mm_Horizontal</footprint>
      <datasheet>http://www.vishay.com/docs/88503/1n4001.pdf</datasheet>
      <libsource lib="Diode" part="1N4007" description="1000V 1A General Purpose Rectifier Diode, DO-41"/>
      <property name="Sheetname" value=""/>
      <property name="Sheetfile" value="File: VCU.kicad_sch"/>
      <sheetpath names="/" tstamps="/"/>
      <tstamps>6f6ddf18-a1b5-4a83-a6a8-d40cd187764a</tstamps>
    </comp>
    <comp ref="H1">
      <value>MountingHole_Pad</value>
      <footprint>MountingHole:MountingHole_2.2mm_M2_Pad</footprint>
      <libsource lib="Mechanical" part="MountingHole_Pad" description="Mounting Hole with connection"/>
      <property name="Sheetname" value=""/>
      <property name="Sheetfile" value="File: VCU.kicad_sch"/>
      <sheetpath names="/" tstamps="/"/>
      <tstamps>65652a24-9140-4a5b-a5be-e18af3b0515a</tstamps>
    </comp>
    <comp ref="H2">
      <value>MountingHole</value>
      <footprint>MountingHole:MountingHole_2.2mm_M2</footprint>
      <libsource lib="Mechanical" part="MountingHole" description="Mounting Hole without connection"/>
      <property name="Sheetname" value=""/>
      <property name="Sheetfile" value="File: VCU.kicad_sch"/>
      <sheetpath names="/" tstamps="/"/>
      <tstamps>9577d977-d753-4c67-b53a-b228e77cf1e7</tstamps>
    </comp>
    <comp ref="H3">
      <value>MountingHole</value>
      <footprint>MountingHole:MountingHole_2.2mm_M2</footprint>
      <libsource lib="Mechanical" part="MountingHole" description="Mounting Hole without connection"/>
      <property name="Sheetname" value=""/>
      <property name="Sheetfile" value="File: VCU.kicad_sch"/>
      <sheetpath names="/" tstamps="/"/>
      <tstamps>61d279fd-4a19-4952-812f-435776878d30</tstamps>
    </comp>
    <comp ref="H4">
      <value>MountingHole</value>
      <footprint>MountingHole:MountingHole_2.2mm_M2</footprint>
      <libsource lib="Mechanical" part="MountingHole" description="Mounting Hole without connection"/>
      <property name="Sheetname" value=""/>
      <property name="Sheetfile" value="File: VCU.kicad_sch"/>
      <sheetpath names="/" tstamps="/"/>
      <tstamps>ae4c4064-8fb8-43f1-8d2f-0e59030e2240</tstamps>
    </comp>
    <comp ref="J1">
      <value>LEMO6</value>
      <footprint>TerminalBlock_4Ucon:TerminalBlock_4Ucon_1x06_P3.50mm_Horizontal</footprint>
      <datasheet> ~</datasheet>
      <libsource lib="Connector" part="LEMO6" description="6-pin LEMO connector"/>
      <property name="Sheetname" value=""/>
      <property name="Sheetfile" value="File: VCU.kicad_sch"/>
      <sheetpath names="/" tstamps="/"/>
      <tstamps>c09490f2-ec3b-49dc-9af9-b430d68a0c08</tstamps>
    </comp>
    <comp ref="J2">
      <value>LEMO4</value>
      <footprint>Connector_JST:JST_EH_B4B-EH-A_1x04_P2.50mm_Vertical</footprint>
      <datasheet> ~</datasheet>
      <libsource lib="Connector" part="LEMO4" description="4-pin LEMO connector"/>
      <property name="Sheetname" value=""/>
      <property name="Sheetfile" value="File: VCU.kicad_sch"/>
      <sheetpath names="/" tstamps="/"/>
      <tstamps>cafb99e1-86af-43cb-b2a0-d07c4d75290b</tstamps>
    </comp>
    <comp ref="J3">
      <value>Conn_01x10_Male</value>
      <footprint>Connector_Molex:Molex_SL_171971-0010_1x10_P2.54mm_Vertical</footprint>
      <libsource lib="Connector" part="Conn_01x10_Male" description="Generic connector, single row, 01x10, script generated (kicad-library-utils/schlib/autogen/connector/)"/>
      <property name="Sheetname" value=""/>
      <property name="Sheetfile" value="File: VCU.kicad_sch"/>
      <sheetpath names="/" tstamps="/"/>
      <tstamps>6839c61b-03ff-4035-802d-9dbafb1a32a1</tstamps>
    </comp>
    <comp ref="J4">
      <value>Conn_01x04_Male</value>
      <footprint>Connector_JST:JST_XH_B4B-XH-A_1x04_P2.50mm_Vertical</footprint>
      <libsource lib="Connector" part="Conn_01x04_Male" description="Generic connector, single row, 01x04, script generated (kicad-library-utils/schlib/autogen/connector/)"/>
      <property name="Sheetname" value=""/>
      <property name="Sheetfile" value="File: VCU.kicad_sch"/>
      <sheetpath names="/" tstamps="/"/>
      <tstamps>6836fce2-5704-455b-9927-5624407f5bc9</tstamps>
    </comp>
    <comp ref="J5">
      <value>Conn_Coaxial</value>
      <footprint>Connector_Coaxial:BNC_TEConnectivity_1478204_Vertical</footprint>
      <datasheet> ~</datasheet>
      <libsource lib="Connector" part="Conn_Coaxial" description="coaxial connector (BNC, SMA, SMB, SMC, Cinch/RCA, LEMO, ...)"/>
      <property name="Sheetname" value=""/>
      <property name="Sheetfile" value="File: VCU.kicad_sch"/>
      <sheetpath names="/" tstamps="/"/>
      <tstamps>592d9bcf-4a3b-4cf9-ae1a-63bc8a29f251</tstamps>
    </comp>
    <comp ref="L1">
      <value>1uf</value>
      <footprint>Inductor_THT:L_Axial_L5.3mm_D2.2mm_P10.16mm_Horizontal_Vishay_IM-1</footprint>
      <libsource lib="Device" part="L" description="Inductor"/>
      <property name="Sheetname" value=""/>
      <property name="Sheetfile" value="File: VCU.kicad_sch"/>
      <sheetpath names="/" tstamps="/"/>
      <tstamps>9f17a761-7fa3-464a-8492-7acd0d6203f9</tstamps>
    </comp>
    <comp ref="L2">
      <value>1uf</value>
      <footprint>Inductor_THT:L_Axial_L5.3mm_D2.2mm_P10.16mm_Horizontal_Vishay_IM-1</footprint>
      <libsource lib="Device" part="L" description="Inductor"/>
      <property name="Sheetname" value=""/>
      <property name="Sheetfile" value="File: VCU.kicad_sch"/>
      <sheetpath names="/" tstamps="/"/>
      <tstamps>204c855b-d251-48bc-887d-f879e5d27678</tstamps>
    </comp>
    <comp ref="R1">
      <value>10k</value>
      <footprint>Resistor_THT:R_Axial_DIN0207_L6.3mm_D2.5mm_P10.16mm_Horizontal</footprint>
      <libsource lib="Device" part="R" description="Resistor"/>
      <property name="Sheetname" value=""/>
      <property name="Sheetfile" value="File: VCU.kicad_sch"/>
      <sheetpath names="/" tstamps="/"/>
      <tstamps>be98f639-57e7-412e-b724-09dddca07d04</tstamps>
    </comp>
    <comp ref="R2">
      <value>10k</value>
      <footprint>Resistor_THT:R_Axial_DIN0207_L6.3mm_D2.5mm_P10.16mm_Horizontal</footprint>
      <libsource lib="Device" part="R" description="Resistor"/>
      <property name="Sheetname" value=""/>
      <property name="Sheetfile" value="File: VCU.kicad_sch"/>
      <sheetpath names="/" tstamps="/"/>
      <tstamps>0de400a8-8022-4a3a-b3ed-3be137d93928</tstamps>
    </comp>
    <comp ref="R3">
      <value>50R</value>
      <footprint>Resistor_THT:R_Axial_DIN0207_L6.3mm_D2.5mm_P10.16mm_Horizontal</footprint>
      <libsource lib="Device" part="R" description="Resistor"/>
      <property name="Sheetname" value=""/>
      <property name="Sheetfile" value="File: VCU.kicad_sch"/>
      <sheetpath names="/" tstamps="/"/>
      <tstamps>2e3f8320-a514-41e7-abd2-738d03ecf634</tstamps>
    </comp>
    <comp ref="R4">
      <value>50R</value>
      <footprint>Resistor_THT:R_Axial_DIN0207_L6.3mm_D2.5mm_P10.16mm_Horizontal</footprint>
      <libsource lib="Device" part="R" description="Resistor"/>
      <property name="Sheetname" value=""/>
      <property name="Sheetfile" value="File: VCU.kicad_sch"/>
      <sheetpath names="/" tstamps="/"/>
      <tstamps>eb19991c-73d1-4207-983e-ed43f5d6a0c5</tstamps>
    </comp>
    <comp ref="R5">
      <value>75R</value>
      <footprint>Resistor_THT:R_Axial_DIN0207_L6.3mm_D2.5mm_P10.16mm_Horizontal</footprint>
      <libsource lib="Device" part="R" description="Resistor"/>
      <property name="Sheetname" value=""/>
      <property name="Sheetfile" value="File: VCU.kicad_sch"/>
      <sheetpath names="/" tstamps="/"/>
      <tstamps>00c0ec12-d8a1-407f-a17d-c31c4d06e0de</tstamps>
    </comp>
    <comp ref="R6">
      <value>10k</value>
      <footprint>Resistor_THT:R_Axial_DIN0207_L6.3mm_D2.5mm_P10.16mm_Horizontal</footprint>
      <libsource lib="Device" part="R" description="Resistor"/>
      <property name="Sheetname" value=""/>
      <property name="Sheetfile" value="File: VCU.kicad_sch"/>
      <sheetpath names="/" tstamps="/"/>
      <tstamps>35c9e231-9b53-46fd-8c1e-63201b8c283d</tstamps>
    </comp>
    <comp ref="U1">
      <value>EL2140</value>
      <footprint>Package_DIP:DIP-8_W7.62mm</footprint>
      <libsource lib="" part="EL2140_1" description=""/>
      <property name="Sheetname" value=""/>
      <property name="Sheetfile" value="File: VCU.kicad_sch"/>
      <sheetpath names="/" tstamps="/"/>
      <tstamps>c10acd74-6da6-451f-bce0-40b40d20967d</tstamps>
    </comp>
    <comp ref="U2">
      <value>LM7808_TO220</value>
      <footprint>Package_TO_SOT_THT:TO-220-3_Vertical</footprint>
      <datasheet>https://www.onsemi.cn/PowerSolutions/document/MC7800-D.PDF</datasheet>
      <libsource lib="Regulator_Linear" part="LM7808_TO220" description="Positive 1A 35V Linear Regulator, Fixed Output 8V, TO-220"/>
      <property name="Sheetname" value=""/>
      <property name="Sheetfile" value="File: VCU.kicad_sch"/>
      <sheetpath names="/" tstamps="/"/>
      <tstamps>3c74a70c-b875-4425-992b-78341c649368</tstamps>
    </comp>
  </components>
  <libparts>
    <libpart lib="" part="C_Polarized_1">
      <description>Polarized capacitor</description>
      <docs>~</docs>
      <footprints>
        <fp>CP_*</fp>
      </footprints>
      <fields>
        <field name="Reference">C</field>
        <field name="Value">C_Polarized_1</field>
        <field name="Datasheet">~</field>
      </fields>
      <pins>
        <pin num="1" name="" type="passive"/>
        <pin num="2" name="" type="passive"/>
      </pins>
    </libpart>
    <libpart lib="" part="EL2140_1">
      <fields>
        <field name="Reference">U</field>
        <field name="Value">EL2140_1</field>
      </fields>
      <pins>
        <pin num="1" name="Vin" type="input"/>
        <pin num="2" name="NC" type="no_connect"/>
        <pin num="3" name="Vinb" type="input"/>
        <pin num="4" name="Vref" type="input"/>
        <pin num="5" name="Voutb" type="output"/>
        <pin num="6" name="Vcc" type="power_out"/>
        <pin num="7" name="Vee" type="power_out"/>
        <pin num="8" name="Vout" type="output"/>
      </pins>
    </libpart>
    <libpart lib="Connector" part="Conn_01x04_Male">
      <description>Generic connector, single row, 01x04, script generated (kicad-library-utils/schlib/autogen/connector/)</description>
      <docs>~</docs>
      <footprints>
        <fp>Connector*:*_1x??_*</fp>
      </footprints>
      <fields>
        <field name="Reference">J</field>
        <field name="Value">Conn_01x04_Male</field>
        <field name="Datasheet">~</field>
      </fields>
      <pins>
        <pin num="1" name="Pin_1" type="passive"/>
        <pin num="2" name="Pin_2" type="passive"/>
        <pin num="3" name="Pin_3" type="passive"/>
        <pin num="4" name="Pin_4" type="passive"/>
      </pins>
    </libpart>
    <libpart lib="Connector" part="Conn_01x10_Male">
      <description>Generic connector, single row, 01x10, script generated (kicad-library-utils/schlib/autogen/connector/)</description>
      <docs>~</docs>
      <footprints>
        <fp>Connector*:*_1x??_*</fp>
      </footprints>
      <fields>
        <field name="Reference">J</field>
        <field name="Value">Conn_01x10_Male</field>
        <field name="Datasheet">~</field>
      </fields>
      <pins>
        <pin num="1" name="Pin_1" type="passive"/>
        <pin num="2" name="Pin_2" type="passive"/>
        <pin num="3" name="Pin_3" type="passive"/>
        <pin num="4" name="Pin_4" type="passive"/>
        <pin num="5" name="Pin_5" type="passive"/>
        <pin num="6" name="Pin_6" type="passive"/>
        <pin num="7" name="Pin_7" type="passive"/>
        <pin num="8" name="Pin_8" type="passive"/>
        <pin num="9" name="Pin_9" type="passive"/>
        <pin num="10" name="Pin_10" type="passive"/>
      </pins>
    </libpart>
    <libpart lib="Connector" part="Conn_Coaxial">
      <description>coaxial connector (BNC, SMA, SMB, SMC, Cinch/RCA, LEMO, ...)</description>
      <docs> ~</docs>
      <footprints>
        <fp>*BNC*</fp>
        <fp>*SMA*</fp>
        <fp>*SMB*</fp>
        <fp>*SMC*</fp>
        <fp>*Cinch*</fp>
        <fp>*LEMO*</fp>
      </footprints>
      <fields>
        <field name="Reference">J</field>
        <field name="Value">Conn_Coaxial</field>
        <field name="Datasheet"> ~</field>
      </fields>
      <pins>
        <pin num="1" name="In" type="passive"/>
        <pin num="2" name="Ext" type="passive"/>
      </pins>
    </libpart>
    <libpart lib="Connector" part="LEMO4">
      <description>4-pin LEMO connector</description>
      <docs> ~</docs>
      <fields>
        <field name="Reference">J</field>
        <field name="Value">LEMO4</field>
        <field name="Datasheet"> ~</field>
      </fields>
      <pins>
        <pin num="1" name="" type="passive"/>
        <pin num="2" name="" type="passive"/>
        <pin num="3" name="" type="passive"/>
        <pin num="4" name="" type="passive"/>
      </pins>
    </libpart>
    <libpart lib="Connector" part="LEMO6">
      <description>6-pin LEMO connector</description>
      <docs> ~</docs>
      <fields>
        <field name="Reference">J</field>
        <field name="Value">LEMO6</field>
        <field name="Datasheet"> ~</field>
      </fields>
      <pins>
        <pin num="1" name="" type="passive"/>
        <pin num="2" name="" type="passive"/>
        <pin num="3" name="" type="passive"/>
        <pin num="4" name="" type="passive"/>
        <pin num="5" name="" type="passive"/>
        <pin num="6" name="" type="passive"/>
      </pins>
    </libpart>
    <libpart lib="Device" part="C">
      <description>Unpolarized capacitor</description>
      <docs>~</docs>
      <footprints>
        <fp>C_*</fp>
      </footprints>
      <fields>
        <field name="Reference">C</field>
        <field name="Value">C</field>
        <field name="Datasheet">~</field>
      </fields>
      <pins>
        <pin num="1" name="" type="passive"/>
        <pin num="2" name="" type="passive"/>
      </pins>
    </libpart>
    <libpart lib="Device" part="C_Polarized">
      <description>Polarized capacitor</description>
      <docs>~</docs>
      <footprints>
        <fp>CP_*</fp>
      </footprints>
      <fields>
        <field name="Reference">C</field>
        <field name="Value">C_Polarized</field>
        <field name="Datasheet">~</field>
      </fields>
      <pins>
        <pin num="1" name="" type="passive"/>
        <pin num="2" name="" type="passive"/>
      </pins>
    </libpart>
    <libpart lib="Device" part="L">
      <description>Inductor</description>
      <docs>~</docs>
      <footprints>
        <fp>Choke_*</fp>
        <fp>*Coil*</fp>
        <fp>Inductor_*</fp>
        <fp>L_*</fp>
      </footprints>
      <fields>
        <field name="Reference">L</field>
        <field name="Value">L</field>
        <field name="Datasheet">~</field>
      </fields>
      <pins>
        <pin num="1" name="1" type="passive"/>
        <pin num="2" name="2" type="passive"/>
      </pins>
    </libpart>
    <libpart lib="Device" part="R">
      <description>Resistor</description>
      <docs>~</docs>
      <footprints>
        <fp>R_*</fp>
      </footprints>
      <fields>
        <field name="Reference">R</field>
        <field name="Value">R</field>
        <field name="Datasheet">~</field>
      </fields>
      <pins>
        <pin num="1" name="" type="passive"/>
        <pin num="2" name="" type="passive"/>
      </pins>
    </libpart>
    <libpart lib="Diode" part="1N4007">
      <description>1000V 1A General Purpose Rectifier Diode, DO-41</description>
      <docs>http://www.vishay.com/docs/88503/1n4001.pdf</docs>
      <footprints>
        <fp>D*DO?41*</fp>
      </footprints>
      <fields>
        <field name="Reference">D</field>
        <field name="Value">1N4007</field>
        <field name="Footprint">Diode_THT:D_DO-41_SOD81_P10.16mm_Horizontal</field>
        <field name="Datasheet">http://www.vishay.com/docs/88503/1n4001.pdf</field>
      </fields>
      <pins>
        <pin num="1" name="K" type="passive"/>
        <pin num="2" name="A" type="passive"/>
      </pins>
    </libpart>
    <libpart lib="Mechanical" part="MountingHole">
      <description>Mounting Hole without connection</description>
      <docs>~</docs>
      <footprints>
        <fp>MountingHole*</fp>
      </footprints>
      <fields>
        <field name="Reference">H</field>
        <field name="Value">MountingHole</field>
        <field name="Datasheet">~</field>
      </fields>
    </libpart>
    <libpart lib="Mechanical" part="MountingHole_Pad">
      <description>Mounting Hole with connection</description>
      <docs>~</docs>
      <footprints>
        <fp>MountingHole*Pad*</fp>
      </footprints>
      <fields>
        <field name="Reference">H</field>
        <field name="Value">MountingHole_Pad</field>
        <field name="Datasheet">~</field>
      </fields>
      <pins>
        <pin num="1" name="1" type="input"/>
      </pins>
    </libpart>
    <libpart lib="Regulator_Linear" part="LM7808_TO220">
      <description>Positive 1A 35V Linear Regulator, Fixed Output 8V, TO-220</description>
      <docs>https://www.onsemi.cn/PowerSolutions/document/MC7800-D.PDF</docs>
      <footprints>
        <fp>TO?220*</fp>
      </footprints>
      <fields>
        <field name="Reference">U</field>
        <field name="Value">LM7808_TO220</field>
        <field name="Footprint">Package_TO_SOT_THT:TO-220-3_Vertical</field>
        <field name="Datasheet">https://www.onsemi.cn/PowerSolutions/document/MC7800-D.PDF</field>
      </fields>
      <pins>
        <pin num="1" name="VI" type="power_in"/>
        <pin num="2" name="GND" type="power_in"/>
        <pin num="3" name="VO" type="power_out"/>
      </pins>
    </libpart>
  </libparts>
  <libraries>
    <library logical="Connector">
      <uri>C:\Program Files\KiCad\6.0\share\kicad\symbols\/Connector.kicad_sym</uri>
    </library>
    <library logical="Device">
      <uri>C:\Program Files\KiCad\6.0\share\kicad\symbols\/Device.kicad_sym</uri>
    </library>
    <library logical="Diode">
      <uri>C:\Program Files\KiCad\6.0\share\kicad\symbols\/Diode.kicad_sym</uri>
    </library>
    <library logical="Mechanical">
      <uri>C:\Program Files\KiCad\6.0\share\kicad\symbols\/Mechanical.kicad_sym</uri>
    </library>
    <library logical="Regulator_Linear">
      <uri>C:\Program Files\KiCad\6.0\share\kicad\symbols\/Regulator_Linear.kicad_sym</uri>
    </library>
  </libraries>
  <nets>
    <net code="1" name="+8V">
      <node ref="C4" pin="1" pintype="passive"/>
      <node ref="C5" pin="1" pintype="passive"/>
      <node ref="C6" pin="1" pintype="passive"/>
      <node ref="R1" pin="2" pintype="passive"/>
      <node ref="R2" pin="1" pintype="passive"/>
      <node ref="U1" pin="6" pinfunction="Vcc" pintype="power_out"/>
      <node ref="U2" pin="1" pinfunction="VI" pintype="power_in"/>
    </net>
    <net code="2" name="+12V">
      <node ref="C7" pin="1" pintype="passive"/>
      <node ref="C8" pin="1" pintype="passive"/>
      <node ref="L2" pin="1" pinfunction="1" pintype="passive"/>
      <node ref="U2" pin="3" pinfunction="VO" pintype="power_out"/>
    </net>
    <net code="3" name="/J1_2_to_J3_8">
      <node ref="J1" pin="2" pintype="passive"/>
      <node ref="J3" pin="8" pinfunction="Pin_8" pintype="passive"/>
    </net>
    <net code="4" name="/J3_1_to_L2">
      <node ref="J3" pin="1" pinfunction="Pin_1" pintype="passive"/>
      <node ref="L1" pin="1" pinfunction="1" pintype="passive"/>
    </net>
    <net code="5" name="/TWISTED_PAIR_out_to_J2">
      <node ref="J1" pin="3" pintype="passive"/>
      <node ref="R3" pin="2" pintype="passive"/>
    </net>
    <net code="6" name="/TWISTED_PAIR_outb_to_J2">
      <node ref="J1" pin="4" pintype="passive"/>
      <node ref="R4" pin="2" pintype="passive"/>
    </net>
    <net code="7" name="/Video_1_to_C1">
      <node ref="C1" pin="2" pintype="passive"/>
      <node ref="J4" pin="2" pinfunction="Pin_2" pintype="passive"/>
    </net>
    <net code="8" name="/Video_2_to_J5">
      <node ref="J4" pin="4" pinfunction="Pin_4" pintype="passive"/>
      <node ref="J5" pin="1" pinfunction="In" pintype="passive"/>
    </net>
    <net code="9" name="GND">
      <node ref="C2" pin="2" pintype="passive"/>
      <node ref="C3" pin="2" pintype="passive"/>
      <node ref="C4" pin="2" pintype="passive"/>
      <node ref="C5" pin="2" pintype="passive"/>
      <node ref="C6" pin="2" pintype="passive"/>
      <node ref="C7" pin="2" pintype="passive"/>
      <node ref="C8" pin="2" pintype="passive"/>
      <node ref="H1" pin="1" pinfunction="1" pintype="input"/>
      <node ref="J1" pin="6" pintype="passive"/>
      <node ref="J2" pin="4" pintype="passive"/>
      <node ref="J3" pin="9" pinfunction="Pin_9" pintype="passive"/>
      <node ref="J4" pin="1" pinfunction="Pin_1" pintype="passive"/>
      <node ref="J4" pin="3" pinfunction="Pin_3" pintype="passive"/>
      <node ref="J5" pin="2" pinfunction="Ext" pintype="passive"/>
      <node ref="R5" pin="2" pintype="passive"/>
      <node ref="R6" pin="2" pintype="passive"/>
      <node ref="U1" pin="7" pinfunction="Vee" pintype="power_out"/>
      <node ref="U2" pin="2" pinfunction="GND" pintype="power_in"/>
    </net>
    <net code="10" name="Net-(C1-Pad1)">
      <node ref="C1" pin="1" pintype="passive"/>
      <node ref="C2" pin="1" pintype="passive"/>
      <node ref="R1" pin="1" pintype="passive"/>
      <node ref="R5" pin="1" pintype="passive"/>
      <node ref="U1" pin="1" pinfunction="Vin" pintype="input"/>
    </net>
    <net code="11" name="Net-(C3-Pad1)">
      <node ref="C3" pin="1" pintype="passive"/>
      <node ref="R2" pin="2" pintype="passive"/>
      <node ref="R6" pin="1" pintype="passive"/>
      <node ref="U1" pin="3" pinfunction="Vinb" pintype="input"/>
      <node ref="U1" pin="4" pinfunction="Vref" pintype="input"/>
    </net>
    <net code="12" name="Net-(D1-Pad1)">
      <node ref="D1" pin="1" pinfunction="K" pintype="passive"/>
      <node ref="J2" pin="1" pintype="passive"/>
    </net>
    <net code="13" name="Net-(D1-Pad2)">
      <node ref="D1" pin="2" pinfunction="A" pintype="passive"/>
      <node ref="J2" pin="2" pintype="passive"/>
      <node ref="L1" pin="2" pinfunction="2" pintype="passive"/>
    </net>
    <net code="14" name="Net-(J3-Pad2)">
      <node ref="J3" pin="2" pinfunction="Pin_2" pintype="passive"/>
      <node ref="J3" pin="4" pinfunction="Pin_4" pintype="passive"/>
    </net>
    <net code="15" name="Net-(J3-Pad7)">
      <node ref="J3" pin="7" pinfunction="Pin_7" pintype="passive"/>
      <node ref="L2" pin="2" pinfunction="2" pintype="passive"/>
    </net>
    <net code="16" name="Net-(R3-Pad1)">
      <node ref="R3" pin="1" pintype="passive"/>
      <node ref="U1" pin="8" pinfunction="Vout" pintype="output"/>
    </net>
    <net code="17" name="Net-(R4-Pad1)">
      <node ref="R4" pin="1" pintype="passive"/>
      <node ref="U1" pin="5" pinfunction="Voutb" pintype="output"/>
    </net>
    <net code="18" name="unconnected-(J1-Pad1)">
      <node ref="J1" pin="1" pintype="passive+no_connect"/>
    </net>
    <net code="19" name="unconnected-(J1-Pad5)">
      <node ref="J1" pin="5" pintype="passive+no_connect"/>
    </net>
    <net code="20" name="unconnected-(J2-Pad3)">
      <node ref="J2" pin="3" pintype="passive+no_connect"/>
    </net>
    <net code="21" name="unconnected-(J3-Pad3)">
      <node ref="J3" pin="3" pinfunction="Pin_3" pintype="passive+no_connect"/>
    </net>
    <net code="22" name="unconnected-(J3-Pad5)">
      <node ref="J3" pin="5" pinfunction="Pin_5" pintype="passive+no_connect"/>
    </net>
    <net code="23" name="unconnected-(J3-Pad6)">
      <node ref="J3" pin="6" pinfunction="Pin_6" pintype="passive+no_connect"/>
    </net>
    <net code="24" name="unconnected-(J3-Pad10)">
      <node ref="J3" pin="10" pinfunction="Pin_10" pintype="passive+no_connect"/>
    </net>
    <net code="25" name="unconnected-(U1-Pad2)">
      <node ref="U1" pin="2" pinfunction="NC" pintype="no_connect"/>
    </net>
  </nets>
</export>
